abstract_shapes/__init__.py
abstract_shapes/abstractShapeManager.py
abstract_shapes/cardinalDirections.py
abstract_shapes/direction.py
abstract_shapes/fileAssociations.py
abstract_shapes/file_associations.py
abstract_shapes/transform.py
abstract_shapes-0.0.0.74.dist-info/METADATA
abstract_shapes-0.0.0.74.dist-info/WHEEL
abstract_shapes-0.0.0.74.dist-info/top_level.txt
abstract_shapes-0.0.0.74.dist-info/RECORD
